digi.v
// Qucs 0.0.18  /home/ynakanishi/.qucs/test_prj/test.sch

`timescale 1ps/100fs

module xnor3( A, Y, B, C ) ;
	input A, B, C ;
	output Y ;
	assign Y = ~(A^B^C) ;
endmodule



module TestBench ();
  wire netC1;
  wire netC2;
  wire netC4;
  wire netYQ;
  wire netYV;

  assign netYQ = netC4 ^~ netC2 ^~ netC1;

  // C1 digital source
  assign netC1 = net_srcC1netC1;
  reg    net_srcC1netC1;
  always begin
    net_srcC1netC1 = 0;
    #1;
    net_srcC1netC1 = !net_srcC1netC1;
    #1;
  end

  // C2 digital source
  assign netC2 = net_srcC2netC2;
  reg    net_srcC2netC2;
  always begin
    net_srcC2netC2 = 0;
    #2;
    net_srcC2netC2 = !net_srcC2netC2;
    #2;
  end

  // C4 digital source
  assign netC4 = net_srcC4netC4;
  reg    net_srcC4netC4;
  always begin
    net_srcC4netC4 = 0;
    #4;
    net_srcC4netC4 = !net_srcC4netC4;
    #4;
  end
  xnor3 X1 (netC1, netYV, netC2, netC4);

  initial begin
    $dumpfile("digi.vcd");
    $dumpvars();
    #8 $finish;
  end

endmodule // TestBench

digi.vcd
$date
	Fri Jun  5 22:49:07 2020
$end
$version
	Icarus Verilog
$end
$timescale
	100fs
$end
$scope module TestBench $end
$var wire 1 ! netYQ $end
$var wire 1 " netYV $end
$var wire 1 # netC4 $end
$var wire 1 $ netC2 $end
$var wire 1 % netC1 $end
$var reg 1 % net_srcC1netC1 $end
$var reg 1 $ net_srcC2netC2 $end
$var reg 1 # net_srcC4netC4 $end
$scope module X1 $end
$var wire 1 % A $end
$var wire 1 $ B $end
$var wire 1 # C $end
$var wire 1 " Y $end
$upscope $end
$upscope $end
$enddefinitions $end
#0
$dumpvars
0%
0$
0#
1"
0!
$end
#10
0"
1!
1%
#20
0%
1$
#30
1"
0!
1%
#40
0"
1!
0%
0$
1#
#50
1"
0!
1%
#60
0%
1$
#70
0"
1!
1%
#80
1"
0!
0%
0$
0#
