digi.v
// Qucs 0.0.18  C:/Users/ynakanishi/.qucs/ensyu_prj/3-3.sch

`timescale 1ps/100fs

module oddeven_counter( RST, OUT2, CLK, OUT1, K, OUT0 ) ;
	input CLK, RST, K ;
	output OUT2, OUT1, OUT0 ;
	reg [2:0] CNT ;
	assign {OUT2, OUT1, OUT0} = CNT ;
	always @( posedge CLK or negedge RST )
	if ( RST == 0 )
		CNT <= 0 ;
	else
	begin
		CNT[2] <= (CNT[2] & ~CNT[1])|(~K & ~CNT[2] & CNT[1])|(K & CNT[2] & ~CNT[0])|(~CNT[2] & CNT[1] & CNT[0]);
		CNT[1] <= (~K & ~CNT[1])|(~CNT[1] & CNT[0])|(K & CNT[1] & ~CNT[0]);
		CNT[0] <= K | (CNT[2] & CNT[1] & ~CNT[0]);
	end
endmodule

module TestBench ();
  wire netOUT0;
  wire netOUT1;
  wire netOUT2;
  wire net_net0;
  wire net_net1;
  wire net_net2;

  oddeven_counter OE (net_net1, netOUT2, net_net0, netOUT1, net_net2, netOUT0);

  // RST digital source
  assign net_net1 = net_srcRSTnet_net1;
  reg    net_srcRSTnet_net1;
  always begin
    net_srcRSTnet_net1 = 0;
    #1000;
    net_srcRSTnet_net1 = 1;
    #100000;
  end

  // CLK digital source
  assign net_net0 = net_srcCLKnet_net0;
  reg    net_srcCLKnet_net0;
  always begin
    net_srcCLKnet_net0 = 0;
    #1000;
    net_srcCLKnet_net0 = 1;
    #1000;
  end

  // K digital source
  assign net_net2 = net_srcKnet_net2;
  reg    net_srcKnet_net2;
  always begin
    net_srcKnet_net2 = 0;
    #13000;
    net_srcKnet_net2 = 1;
    #9000;
  end

  initial begin
    $dumpfile("digi.vcd");
    $dumpvars();
    #50000 $finish;
  end

endmodule // TestBench

digi.vcd
$date
	Sat Jul 18 01:29:28 2020
$end
$version
	Icarus Verilog
$end
$timescale
	100fs
$end
$scope module TestBench $end
$var wire 1 ! net_net0 $end
$var wire 1 " net_net1 $end
$var wire 1 # net_net2 $end
$var wire 1 $ netOUT2 $end
$var wire 1 % netOUT1 $end
$var wire 1 & netOUT0 $end
$var reg 1 ' net_srcCLKnet_net0 $end
$var reg 1 ( net_srcKnet_net2 $end
$var reg 1 ) net_srcRSTnet_net1 $end
$scope module OE $end
$var wire 1 ! CLK $end
$var wire 1 # K $end
$var wire 1 " RST $end
$var wire 1 $ OUT2 $end
$var wire 1 % OUT1 $end
$var wire 1 & OUT0 $end
$var reg 3 * CNT [2:0] $end
$upscope $end
$upscope $end
$enddefinitions $end
#0
$dumpvars
b0 *
0)
0(
0'
0&
0%
0$
0#
0"
0!
$end
#10000
1%
b10 *
1!
1'
1"
1)
#20000
0!
0'
#30000
0%
1$
b100 *
1!
1'
#40000
0!
0'
#50000
1%
b110 *
1!
1'
#60000
0!
0'
#70000
1&
0%
0$
b1 *
1!
1'
#80000
0!
0'
#90000
0&
1%
b10 *
1!
1'
#100000
0!
0'
#110000
0%
1$
b100 *
1!
1'
#120000
0!
0'
#130000
1&
b101 *
1!
1'
1#
1(
#140000
0!
0'
#150000
1%
b111 *
1!
1'
#160000
0!
0'
#170000
0%
0$
b1 *
1!
1'
#180000
0!
0'
#190000
1%
b11 *
1!
1'
#200000
0!
0'
#210000
0%
1$
b101 *
1!
1'
#220000
0!
0'
0#
0(
#230000
0&
1%
b110 *
1!
1'
#240000
0!
0'
#250000
1&
0%
0$
b1 *
1!
1'
#260000
0!
0'
#270000
0&
1%
b10 *
1!
1'
#280000
0!
0'
#290000
0%
1$
b100 *
1!
1'
#300000
0!
0'
#310000
1%
b110 *
1!
1'
#320000
0!
0'
#330000
1&
0%
0$
b1 *
1!
1'
#340000
0!
0'
#350000
1%
b11 *
1!
1'
1#
1(
#360000
0!
0'
#370000
0%
1$
b101 *
1!
1'
#380000
0!
0'
#390000
1%
b111 *
1!
1'
#400000
0!
0'
#410000
0%
0$
b1 *
1!
1'
#420000
0!
0'
#430000
1%
b11 *
1!
1'
#440000
0!
0'
0#
0(
#450000
0&
0%
1$
b100 *
1!
1'
#460000
0!
0'
#470000
1%
b110 *
1!
1'
#480000
0!
0'
#490000
1&
0%
0$
b1 *
1!
1'
#500000
0!
0'
